{"cameraMode":{"drawMode":0,"name":"Shaded","section":"Shading Mode"},"sceneLighting":true,"audioPlay":false,"sceneViewState":{"m_AlwaysRefresh":false,"showFog":false,"showSkybox":true,"showFlares":true,"showImageEffects":true,"showParticleSystems":true,"showVisualEffectGraphs":true,"m_FxEnabled":true},"in2DMode":false,"pivot":{"x":2.259521484375,"y":-7.079986572265625,"z":-2.1859130859375},"rotation":{"x":-0.3951546251773834,"y":-0.5156405568122864,"z":0.2896541357040405,"w":-0.7034501433372498},"size":5.966026306152344,"orthographic":false}